setup.cfg
setup.py
trireme/__init__.py
trireme/trireme.py
trireme.egg-info/PKG-INFO
trireme.egg-info/SOURCES.txt
trireme.egg-info/dependency_links.txt
trireme.egg-info/requires.txt
trireme.egg-info/top_level.txt
trireme/migrators/__init__.py
trireme/migrators/cassandra.py
trireme/migrators/data.py
trireme/migrators/solr.py