Metadata-Version: 1.1
Name: trireme
Version: 1.3.1
Summary: Migration tool providing support for Apache Cassandra, DataStax Enterprise Cassandra, & DataStax Enterprise Solr.
Home-page: https://github.com/o19s/trireme
Author: Christopher Bradford
Author-email: cbradford@opensourceconnections.com
License: BSD
Download-URL: https://github.com/o19s/trireme/tarball/v1.3.1
Keywords: cassandra solr dse dsc migrations development
Platform: UNKNOWN
Classifier: Development Status :: 4 - Beta
Classifier: Intended Audience :: Developers
Classifier: Topic :: Software Development :: Build Tools
Classifier: Programming Language :: Python :: 3
Classifier: Programming Language :: Python :: 2
